pygamecfg/__init__.py
pygamecfg/__main__.py
pygamecfg/common_ut.py
pygamecfg/core_gamecfg.py
pygamecfg/game_cod4.py
pygamecfg/game_cod4_gungame.py
pygamecfg/game_cod4_promod.py
pygamecfg/game_ut2k4.py
pygamecfg/game_ut99.py
pygamecfg/py.typed
pygamecfg/tool_ini.py
pygamecfg-0.4.3.dist-info/LICENSE.md
pygamecfg-0.4.3.dist-info/METADATA
pygamecfg-0.4.3.dist-info/WHEEL
pygamecfg-0.4.3.dist-info/top_level.txt
pygamecfg-0.4.3.dist-info/RECORD
