Metadata-Version: 2.1
Name: pygamecfg
Version: 0.4.3
Summary: A simple game config tool that provide bash API to read / write game config files (cod, ut ...)
Author-email: chacha <1000CHACHA0001@gmail.com>
Maintainer-email: chacha <1000CHACHA0001@gmail.com>
License: # License
Project-URL: Homepage, https://chacha.ddns.net/gitea/chacha/pygamecfg
Project-URL: Documentation, https://chacha.ddns.net/mkdocs-web/chacha/pygamecfg/master/latest/
Project-URL: Tracker, https://chacha.ddns.net/gitea/chacha/pygamecfg/issues
Keywords: chacha,chacha,template,pygamecfg
Platform: any
Classifier: Development Status :: 4 - Beta
Classifier: Programming Language :: Python :: 3 :: Only
Classifier: Programming Language :: Python :: 3.9
Requires-Python: >=3.9
License-File: LICENSE.md
Requires-Dist: packaging
Requires-Dist: pysimpleini>=0.3.1
Requires-Dist: typed-argument-parser==1.*
Requires-Dist: importlib-metadata; python_version < "3.9"
Provides-Extra: complexity-check
Requires-Dist: chacha-cicd-helper; extra == "complexity-check"
Provides-Extra: coverage-check
Requires-Dist: chacha-cicd-helper; extra == "coverage-check"
Provides-Extra: doc-gen
Requires-Dist: chacha-cicd-helper; extra == "doc-gen"
Provides-Extra: quality-check
Requires-Dist: chacha-cicd-helper; extra == "quality-check"
Provides-Extra: test
Requires-Dist: chacha-cicd-helper; extra == "test"
Provides-Extra: type-check
Requires-Dist: chacha-cicd-helper; extra == "type-check"
